installresourceserver/__init__.py
installresourceserver/installresourceserver.py
InstallResourceServer-0.0.0.dist-info/LICENSE
InstallResourceServer-0.0.0.dist-info/METADATA
InstallResourceServer-0.0.0.dist-info/WHEEL
InstallResourceServer-0.0.0.dist-info/top_level.txt
InstallResourceServer-0.0.0.dist-info/RECORD
